lumeny/__init__.py
lumeny/ai_utils.py
lumeny/caldav_connector.py
lumeny/calendar.py
lumeny/cli.py
lumeny/config_loader.py
lumeny/embedding_generator.py
lumeny/miniflux_connector.py
lumeny/task_picker.py
lumeny/testing.log
lumeny/tui.py
lumeny/utils.py
lumeny-0.3.0.dist-info/METADATA
lumeny-0.3.0.dist-info/WHEEL
lumeny-0.3.0.dist-info/entry_points.txt
lumeny-0.3.0.dist-info/RECORD
