Metadata-Version: 2.1
Name: lumeny
Version: 0.3.0
Summary: A cli and tui based personal management app for Lumen Young
Author: Lumen Young
Author-email: pip@lumeny.io
Requires-Python: >=3.10,<3.12
Classifier: Programming Language :: Python :: 3
Classifier: Programming Language :: Python :: 3.10
Classifier: Programming Language :: Python :: 3.11
Requires-Dist: caldav (>=1.2.1,<2.0.0)
Requires-Dist: click (>=8.1.3,<9.0.0)
Requires-Dist: click-config-file (>=0.6.0,<0.7.0)
Requires-Dist: dateparser (>=1.1.8,<2.0.0)
Requires-Dist: docker (>=6.0.1,<7.0.0)
Requires-Dist: miniflux (>=0.0.15,<0.0.16)
Requires-Dist: nltk (>=3.8.1,<4.0.0)
Requires-Dist: openai (>=0.27.2,<0.28.0)
Requires-Dist: prompt-toolkit (>=3.0.38,<4.0.0)
Requires-Dist: pyyaml (>=6.0,<7.0)
Requires-Dist: qdrant-client (>=1.1.0,<2.0.0)
Requires-Dist: questionary (>=1.10.0,<2.0.0)
Requires-Dist: termcolor (>=2.3.0,<3.0.0)
Requires-Dist: textual (>=0.16.0,<0.17.0)
